azure/mgmt/support/__init__.py
azure/mgmt/support/_configuration.py
azure/mgmt/support/_microsoft_support.py
azure/mgmt/support/_patch.py
azure/mgmt/support/_serialization.py
azure/mgmt/support/_vendor.py
azure/mgmt/support/_version.py
azure/mgmt/support/py.typed
azure/mgmt/support/aio/__init__.py
azure/mgmt/support/aio/_configuration.py
azure/mgmt/support/aio/_microsoft_support.py
azure/mgmt/support/aio/_patch.py
azure/mgmt/support/aio/operations/__init__.py
azure/mgmt/support/aio/operations/_chat_transcripts_no_subscription_operations.py
azure/mgmt/support/aio/operations/_chat_transcripts_operations.py
azure/mgmt/support/aio/operations/_communications_no_subscription_operations.py
azure/mgmt/support/aio/operations/_communications_operations.py
azure/mgmt/support/aio/operations/_file_workspaces_no_subscription_operations.py
azure/mgmt/support/aio/operations/_file_workspaces_operations.py
azure/mgmt/support/aio/operations/_files_no_subscription_operations.py
azure/mgmt/support/aio/operations/_files_operations.py
azure/mgmt/support/aio/operations/_operations.py
azure/mgmt/support/aio/operations/_patch.py
azure/mgmt/support/aio/operations/_problem_classifications_operations.py
azure/mgmt/support/aio/operations/_services_operations.py
azure/mgmt/support/aio/operations/_support_tickets_no_subscription_operations.py
azure/mgmt/support/aio/operations/_support_tickets_operations.py
azure/mgmt/support/models/__init__.py
azure/mgmt/support/models/_microsoft_support_enums.py
azure/mgmt/support/models/_models_py3.py
azure/mgmt/support/models/_patch.py
azure/mgmt/support/operations/__init__.py
azure/mgmt/support/operations/_chat_transcripts_no_subscription_operations.py
azure/mgmt/support/operations/_chat_transcripts_operations.py
azure/mgmt/support/operations/_communications_no_subscription_operations.py
azure/mgmt/support/operations/_communications_operations.py
azure/mgmt/support/operations/_file_workspaces_no_subscription_operations.py
azure_mgmt_support-7.0.0.dist-info/LICENSE
azure_mgmt_support-7.0.0.dist-info/METADATA
azure_mgmt_support-7.0.0.dist-info/WHEEL
azure_mgmt_support-7.0.0.dist-info/top_level.txt
azure_mgmt_support-7.0.0.dist-info/RECORD
